{
  "repair:indirect_address_cross_sheet:=IF(INDIRECT(ADDRESS(48+COLUMN(),12,1,1,\"Spielplan\"))=\"ja\",INDIRECT(ADDRESS(IF(MOD(B$1,2)=0,25,12),(ROW()-2)*2+4,1,1,\"1-2\")),\"\")": "=IF(INDIRECT(\"$Spielplan.\" & ADDRESS(48+COLUMN(),12,1,1))=\"ja\",INDIRECT(\"$1-2.\" & ADDRESS(IF(MOD(B$1,2)=0,25,12),(ROW()-2)*2+4,1,1)),\"\")",
  "repair:indirect_address_cross_sheet:=IF(INDIRECT(ADDRESS(48+COLUMN(),12,1,1,\"Spielplan\"))=\"ja\",INDIRECT(ADDRESS(IF(MOD(C$1,2)=0,25,12),(ROW()-2)*2+4,1,1,\"1-2\")),\"\")": "=IF(INDIRECT(\"$Spielplan.\" & ADDRESS(48+COLUMN(),12,1,1))=\"ja\",INDIRECT(\"$1-2.\" & ADDRESS(IF(MOD(C$1,2)=0,25,12),(ROW()-2)*2+4,1,1)),\"\")",
  "repair:indirect_address_cross_sheet:=IF(INDIRECT(ADDRESS(48+COLUMN(),12,1,1,\"Spielplan\"))=\"ja\",INDIRECT(ADDRESS(IF(MOD(D$1,2)=0,25,12),(ROW()-2)*2+4,1,1,\"3-4\")),\"\")": "=IF(INDIRECT(\"$Spielplan.\" & ADDRESS(48+COLUMN(),12,1,1))=\"ja\",INDIRECT(\"$3-4.\" & ADDRESS(IF(MOD(D$1,2)=0,25,12),(ROW()-2)*2+4,1,1)),\"\")",
  "repair:indirect_address_cross_sheet:=IF(INDIRECT(ADDRESS(48+COLUMN(),12,1,1,\"Spielplan\"))=\"ja\",INDIRECT(ADDRESS(IF(MOD(E$1,2)=0,25,12),(ROW()-2)*2+4,1,1,\"3-4\")),\"\")": "=IF(INDIRECT(\"$Spielplan.\" & ADDRESS(48+COLUMN(),12,1,1))=\"ja\",INDIRECT(\"$3-4.\" & ADDRESS(IF(MOD(E$1,2)=0,25,12),(ROW()-2)*2+4,1,1)),\"\")",
  "repair:indirect_address_cross_sheet:=IF(INDIRECT(ADDRESS(48+COLUMN(),12,1,1,\"Spielplan\"))=\"ja\",INDIRECT(ADDRESS(IF(MOD(F$1,2)=0,25,12),(ROW()-2)*2+4,1,1,\"5-6\")),\"\")": "=IF(INDIRECT(\"$Spielplan.\" & ADDRESS(48+COLUMN(),12,1,1))=\"ja\",INDIRECT(\"$5-6.\" & ADDRESS(IF(MOD(F$1,2)=0,25,12),(ROW()-2)*2+4,1,1)),\"\")",
  "repair:indirect_address_cross_sheet:=IF(INDIRECT(ADDRESS(48+COLUMN(),12,1,1,\"Spielplan\"))=\"ja\",INDIRECT(ADDRESS(IF(MOD(G$1,2)=0,25,12),(ROW()-2)*2+4,1,1,\"5-6\")),\"\")": "=IF(INDIRECT(\"$Spielplan.\" & ADDRESS(48+COLUMN(),12,1,1))=\"ja\",INDIRECT(\"$5-6.\" & ADDRESS(IF(MOD(G$1,2)=0,25,12),(ROW()-2)*2+4,1,1)),\"\")",
  "repair:indirect_address_cross_sheet:=IF(INDIRECT(ADDRESS(48+COLUMN(),12,1,1,\"Spielplan\"))=\"ja\",INDIRECT(ADDRESS(IF(MOD(H$1,2)=0,25,12),(ROW()-2)*2+4,1,1,\"7-8\")),\"\")": "=IF(INDIRECT(\"$Spielplan.\" & ADDRESS(48+COLUMN(),12,1,1))=\"ja\",INDIRECT(\"$7-8.\" & ADDRESS(IF(MOD(H$1,2)=0,25,12),(ROW()-2)*2+4,1,1)),\"\")",
  "repair:indirect_address_cross_sheet:=IF(INDIRECT(ADDRESS(48+COLUMN(),12,1,1,\"Spielplan\"))=\"ja\",INDIRECT(ADDRESS(IF(MOD(I$1,2)=0,25,12),(ROW()-2)*2+4,1,1,\"7-8\")),\"\")": "=IF(INDIRECT(\"$Spielplan.\" & ADDRESS(48+COLUMN(),12,1,1))=\"ja\",INDIRECT(\"$7-8.\" & ADDRESS(IF(MOD(I$1,2)=0,25,12),(ROW()-2)*2+4,1,1)),\"\")",
  "repair:indirect_address_cross_sheet:=IF(INDIRECT(ADDRESS(48+COLUMN(),12,1,1,\"Spielplan\"))=\"ja\",INDIRECT(ADDRESS(IF(MOD(J$1,2)=0,25,12),(ROW()-2)*2+4,1,1,\"9-10\")),\"\")": "=IF(INDIRECT(\"$Spielplan.\" & ADDRESS(48+COLUMN(),12,1,1))=\"ja\",INDIRECT(\"$9-10.\" & ADDRESS(IF(MOD(J$1,2)=0,25,12),(ROW()-2)*2+4,1,1)),\"\")",
  "repair:indirect_address_cross_sheet:=IF(INDIRECT(ADDRESS(48+COLUMN(),12,1,1,\"Spielplan\"))=\"ja\",INDIRECT(ADDRESS(IF(MOD(K$1,2)=0,25,12),(ROW()-2)*2+4,1,1,\"9-10\")),\"\")": "=IF(INDIRECT(\"$Spielplan.\" & ADDRESS(48+COLUMN(),12,1,1))=\"ja\",INDIRECT(\"$9-10.\" & ADDRESS(IF(MOD(K$1,2)=0,25,12),(ROW()-2)*2+4,1,1)),\"\")",
  "repair:indirect_address_cross_sheet:=IF(INDIRECT(ADDRESS(48+COLUMN(),12,1,1,\"Spielplan\"))=\"ja\",INDIRECT(ADDRESS(IF(MOD(L$1,2)=0,25,12),(ROW()-2)*2+4,1,1,\"1112\")),\"\")": "=IF(INDIRECT(\"$Spielplan.\" & ADDRESS(48+COLUMN(),12,1,1))=\"ja\",INDIRECT(\"$1112.\" & ADDRESS(IF(MOD(L$1,2)=0,25,12),(ROW()-2)*2+4,1,1)),\"\")",
  "repair:indirect_address_cross_sheet:=IF(INDIRECT(ADDRESS(48+COLUMN(),12,1,1,\"Spielplan\"))=\"ja\",INDIRECT(ADDRESS(IF(MOD(M$1,2)=0,25,12),(ROW()-2)*2+4,1,1,\"1112\")),\"\")": "=IF(INDIRECT(\"$Spielplan.\" & ADDRESS(48+COLUMN(),12,1,1))=\"ja\",INDIRECT(\"$1112.\" & ADDRESS(IF(MOD(M$1,2)=0,25,12),(ROW()-2)*2+4,1,1)),\"\")",
  "repair:indirect_address_cross_sheet:=IF(INDIRECT(ADDRESS(48+COLUMN(),12,1,1,\"Spielplan\"))=\"ja\",INDIRECT(ADDRESS(IF(MOD(N$1,2)=0,25,12),(ROW()-2)*2+4,1,1,\"1314\")),\"\")": "=IF(INDIRECT(\"$Spielplan.\" & ADDRESS(48+COLUMN(),12,1,1))=\"ja\",INDIRECT(\"$1314.\" & ADDRESS(IF(MOD(N$1,2)=0,25,12),(ROW()-2)*2+4,1,1)),\"\")",
  "repair:indirect_address_cross_sheet:=IF(INDIRECT(ADDRESS(48+COLUMN(),12,1,1,\"Spielplan\"))=\"ja\",INDIRECT(ADDRESS(IF(MOD(O$1,2)=0,25,12),(ROW()-2)*2+4,1,1,\"1314\")),\"\")": "=IF(INDIRECT(\"$Spielplan.\" & ADDRESS(48+COLUMN(),12,1,1))=\"ja\",INDIRECT(\"$1314.\" & ADDRESS(IF(MOD(O$1,2)=0,25,12),(ROW()-2)*2+4,1,1)),\"\")",
  "repair:indirect_address_cross_sheet:=IF(INDIRECT(ADDRESS(48+COLUMN(),12,1,1,\"Spielplan\"))=\"ja\",INDIRECT(ADDRESS(IF(MOD(P$1,2)=0,25,12),(ROW()-2)*2+4,1,1,\"1516\")),\"\")": "=IF(INDIRECT(\"$Spielplan.\" & ADDRESS(48+COLUMN(),12,1,1))=\"ja\",INDIRECT(\"$1516.\" & ADDRESS(IF(MOD(P$1,2)=0,25,12),(ROW()-2)*2+4,1,1)),\"\")",
  "repair:indirect_address_cross_sheet:=IF(INDIRECT(ADDRESS(48+COLUMN(),12,1,1,\"Spielplan\"))=\"ja\",INDIRECT(ADDRESS(IF(MOD(Q$1,2)=0,25,12),(ROW()-2)*2+4,1,1,\"1516\")),\"\")": "=IF(INDIRECT(\"$Spielplan.\" & ADDRESS(48+COLUMN(),12,1,1))=\"ja\",INDIRECT(\"$1516.\" & ADDRESS(IF(MOD(Q$1,2)=0,25,12),(ROW()-2)*2+4,1,1)),\"\")",
  "repair:indirect_address_cross_sheet:=IF(INDIRECT(ADDRESS(48+COLUMN(),12,1,1,\"Spielplan\"))=\"ja\",INDIRECT(ADDRESS(IF(MOD(R$1,2)=0,25,12),(ROW()-2)*2+4,1,1,\"1718\")),\"\")": "=IF(INDIRECT(\"$Spielplan.\" & ADDRESS(48+COLUMN(),12,1,1))=\"ja\",INDIRECT(\"$1718.\" & ADDRESS(IF(MOD(R$1,2)=0,25,12),(ROW()-2)*2+4,1,1)),\"\")",
  "repair:indirect_address_cross_sheet:=IF(INDIRECT(ADDRESS(48+COLUMN(),12,1,1,\"Spielplan\"))=\"ja\",INDIRECT(ADDRESS(IF(MOD(S$1,2)=0,25,12),(ROW()-2)*2+4,1,1,\"1718\")),\"\")": "=IF(INDIRECT(\"$Spielplan.\" & ADDRESS(48+COLUMN(),12,1,1))=\"ja\",INDIRECT(\"$1718.\" & ADDRESS(IF(MOD(S$1,2)=0,25,12),(ROW()-2)*2+4,1,1)),\"\")",
  "repair:indirect_address_cross_sheet:=IF(INDIRECT(ADDRESS(48+COLUMN(),12,1,1,\"Spielplan\"))=\"ja\",INDIRECT(ADDRESS(IF(MOD(T$1,2)=0,25,12),(ROW()-2)*2+4,1,1,\"1920\")),\"\")": "=IF(INDIRECT(\"$Spielplan.\" & ADDRESS(48+COLUMN(),12,1,1))=\"ja\",INDIRECT(\"$1920.\" & ADDRESS(IF(MOD(T$1,2)=0,25,12),(ROW()-2)*2+4,1,1)),\"\")",
  "repair:indirect_address_cross_sheet:=IF(INDIRECT(ADDRESS(48+COLUMN(),12,1,1,\"Spielplan\"))=\"ja\",INDIRECT(ADDRESS(IF(MOD(U$1,2)=0,25,12),(ROW()-2)*2+4,1,1,\"1920\")),\"\")": "=IF(INDIRECT(\"$Spielplan.\" & ADDRESS(48+COLUMN(),12,1,1))=\"ja\",INDIRECT(\"$1920.\" & ADDRESS(IF(MOD(U$1,2)=0,25,12),(ROW()-2)*2+4,1,1)),\"\")",
  "repair:indirect_address_cross_sheet:=IF(INDIRECT(ADDRESS(48+COLUMN(),12,1,1,\"Spielplan\"))=\"ja\",INDIRECT(ADDRESS(IF(MOD(V$1,2)=0,25,12),(ROW()-2)*2+4,1,1,\"2122\")),\"\")": "=IF(INDIRECT(\"$Spielplan.\" & ADDRESS(48+COLUMN(),12,1,1))=\"ja\",INDIRECT(\"$2122.\" & ADDRESS(IF(MOD(V$1,2)=0,25,12),(ROW()-2)*2+4,1,1)),\"\")",
  "repair:indirect_address_cross_sheet:=IF(INDIRECT(ADDRESS(48+COLUMN(),12,1,1,\"Spielplan\"))=\"ja\",INDIRECT(ADDRESS(IF(MOD(W$1,2)=0,25,12),(ROW()-2)*2+4,1,1,\"2122\")),\"\")": "=IF(INDIRECT(\"$Spielplan.\" & ADDRESS(48+COLUMN(),12,1,1))=\"ja\",INDIRECT(\"$2122.\" & ADDRESS(IF(MOD(W$1,2)=0,25,12),(ROW()-2)*2+4,1,1)),\"\")",
  "repair:indirect_address_cross_sheet:=IF(INDIRECT(ADDRESS(48+COLUMN(),12,1,1,\"Spielplan\"))=\"ja\",INDIRECT(ADDRESS(IF(MOD(X$1,2)=0,25,12),(ROW()-2)*2+4,1,1,\"2324\")),\"\")": "=IF(INDIRECT(\"$Spielplan.\" & ADDRESS(48+COLUMN(),12,1,1))=\"ja\",INDIRECT(\"$2324.\" & ADDRESS(IF(MOD(X$1,2)=0,25,12),(ROW()-2)*2+4,1,1)),\"\")",
  "repair:indirect_address_cross_sheet:=IF(INDIRECT(ADDRESS(48+COLUMN(),12,1,1,\"Spielplan\"))=\"ja\",INDIRECT(ADDRESS(IF(MOD(Y$1,2)=0,25,12),(ROW()-2)*2+4,1,1,\"2324\")),\"\")": "=IF(INDIRECT(\"$Spielplan.\" & ADDRESS(48+COLUMN(),12,1,1))=\"ja\",INDIRECT(\"$2324.\" & ADDRESS(IF(MOD(Y$1,2)=0,25,12),(ROW()-2)*2+4,1,1)),\"\")",
  "repair:indirect_address_cross_sheet:=IF(INDIRECT(ADDRESS(48+COLUMN(),12,1,1,\"Spielplan\"))=\"ja\",INDIRECT(ADDRESS(IF(MOD(Z$1,2)=0,25,12),(ROW()-2)*2+4,1,1,\"2526\")),\"\")": "=IF(INDIRECT(\"$Spielplan.\" & ADDRESS(48+COLUMN(),12,1,1))=\"ja\",INDIRECT(\"$2526.\" & ADDRESS(IF(MOD(Z$1,2)=0,25,12),(ROW()-2)*2+4,1,1)),\"\")",
  "repair:indirect_address_cross_sheet:=IF(INDIRECT(ADDRESS(48+COLUMN(),12,1,1,\"Spielplan\"))=\"ja\",INDIRECT(ADDRESS(IF(MOD(AA$1,2)=0,25,12),(ROW()-2)*2+4,1,1,\"2526\")),\"\")": "=IF(INDIRECT(\"$Spielplan.\" & ADDRESS(48+COLUMN(),12,1,1))=\"ja\",INDIRECT(\"$2526.\" & ADDRESS(IF(MOD(AA$1,2)=0,25,12),(ROW()-2)*2+4,1,1)),\"\")",
  "repair:indirect_address_cross_sheet:=IF(INDIRECT(ADDRESS(48+COLUMN(),12,1,1,\"Spielplan\"))=\"ja\",INDIRECT(ADDRESS(IF(MOD(AB$1,2)=0,25,12),(ROW()-2)*2+4,1,1,\"2728\")),\"\")": "=IF(INDIRECT(\"$Spielplan.\" & ADDRESS(48+COLUMN(),12,1,1))=\"ja\",INDIRECT(\"$2728.\" & ADDRESS(IF(MOD(AB$1,2)=0,25,12),(ROW()-2)*2+4,1,1)),\"\")",
  "repair:indirect_address_cross_sheet:=IF(INDIRECT(ADDRESS(48+COLUMN(),12,1,1,\"Spielplan\"))=\"ja\",INDIRECT(ADDRESS(IF(MOD(AC$1,2)=0,25,12),(ROW()-2)*2+4,1,1,\"2728\")),\"\")": "=IF(INDIRECT(\"$Spielplan.\" & ADDRESS(48+COLUMN(),12,1,1))=\"ja\",INDIRECT(\"$2728.\" & ADDRESS(IF(MOD(AC$1,2)=0,25,12),(ROW()-2)*2+4,1,1)),\"\")",
  "repair:indirect_address_cross_sheet:=IF(INDIRECT(ADDRESS(48+COLUMN(),12,1,1,\"Spielplan\"))=\"ja\",INDIRECT(ADDRESS(IF(MOD(AD$1,2)=0,25,12),(ROW()-2)*2+4,1,1,\"2930\")),\"\")": "=IF(INDIRECT(\"$Spielplan.\" & ADDRESS(48+COLUMN(),12,1,1))=\"ja\",INDIRECT(\"$2930.\" & ADDRESS(IF(MOD(AD$1,2)=0,25,12),(ROW()-2)*2+4,1,1)),\"\")",
  "repair:indirect_address_cross_sheet:=IF(INDIRECT(ADDRESS(48+COLUMN(),12,1,1,\"Spielplan\"))=\"ja\",INDIRECT(ADDRESS(IF(MOD(AE$1,2)=0,25,12),(ROW()-2)*2+4,1,1,\"2930\")),\"\")": "=IF(INDIRECT(\"$Spielplan.\" & ADDRESS(48+COLUMN(),12,1,1))=\"ja\",INDIRECT(\"$2930.\" & ADDRESS(IF(MOD(AE$1,2)=0,25,12),(ROW()-2)*2+4,1,1)),\"\")",
  "repair:indirect_address_cross_sheet:=IF(INDIRECT(ADDRESS(48+COLUMN(),12,1,1,\"Spielplan\"))=\"ja\",INDIRECT(ADDRESS(IF(MOD(AF$1,2)=0,25,12),(ROW()-2)*2+4,1,1,\"3132\")),\"\")": "=IF(INDIRECT(\"$Spielplan.\" & ADDRESS(48+COLUMN(),12,1,1))=\"ja\",INDIRECT(\"$3132.\" & ADDRESS(IF(MOD(AF$1,2)=0,25,12),(ROW()-2)*2+4,1,1)),\"\")",
  "repair:indirect_address_cross_sheet:=IF(INDIRECT(ADDRESS(48+COLUMN(),12,1,1,\"Spielplan\"))=\"ja\",INDIRECT(ADDRESS(IF(MOD(AG$1,2)=0,25,12),(ROW()-2)*2+4,1,1,\"3132\")),\"\")": "=IF(INDIRECT(\"$Spielplan.\" & ADDRESS(48+COLUMN(),12,1,1))=\"ja\",INDIRECT(\"$3132.\" & ADDRESS(IF(MOD(AG$1,2)=0,25,12),(ROW()-2)*2+4,1,1)),\"\")",
  "repair:indirect_address_cross_sheet:=IF(INDIRECT(ADDRESS(48+COLUMN(),12,1,1,\"Spielplan\"))=\"ja\",INDIRECT(ADDRESS(IF(MOD(AH$1,2)=0,25,12),(ROW()-2)*2+4,1,1,\"3334\")),\"\")": "=IF(INDIRECT(\"$Spielplan.\" & ADDRESS(48+COLUMN(),12,1,1))=\"ja\",INDIRECT(\"$3334.\" & ADDRESS(IF(MOD(AH$1,2)=0,25,12),(ROW()-2)*2+4,1,1)),\"\")",
  "repair:indirect_address_cross_sheet:=IF(INDIRECT(ADDRESS(48+COLUMN(),12,1,1,\"Spielplan\"))=\"ja\",INDIRECT(ADDRESS(IF(MOD(AI$1,2)=0,25,12),(ROW()-2)*2+4,1,1,\"3334\")),\"\")": "=IF(INDIRECT(\"$Spielplan.\" & ADDRESS(48+COLUMN(),12,1,1))=\"ja\",INDIRECT(\"$3334.\" & ADDRESS(IF(MOD(AI$1,2)=0,25,12),(ROW()-2)*2+4,1,1)),\"\")",
  "repair:indirect_address_cross_sheet:=MIN(INDIRECT(\"Spieler!\"&ADDRESS(ROW()-27,2,4,1)&\":\" & ADDRESS(ROW()-27,Tabelle!$D$5+1,4,1),1))": "=MIN(INDIRECT(\"$Spieler.\" & ADDRESS(ROW()-27,2,4,1) & \":\" & \"$Spieler.\" & ADDRESS(ROW()-27,Tabelle!$D$5+1,4,1)))",
  "repair:indirect_address_cross_sheet:=AVERAGE(INDIRECT(\"Spieler!\"&ADDRESS(ROW()-27,2,4,1)&\":\" & ADDRESS(ROW()-27,Tabelle!$D$5+1,4,1),1))": "=AVERAGE(INDIRECT(\"$Spieler.\" & ADDRESS(ROW()-27,2,4,1) & \":\" & \"$Spieler.\" & ADDRESS(ROW()-27,Tabelle!$D$5+1,4,1)))",
  "repair:indirect_address_cross_sheet:=MEDIAN(INDIRECT(\"Spieler!\"&ADDRESS(ROW()-27,2,4,1)&\":\" & ADDRESS(ROW()-27,Tabelle!$D$5+1,4,1),1))": "=MEDIAN(INDIRECT(\"$Spieler.\" & ADDRESS(ROW()-27,2,4,1) & \":\" & \"$Spieler.\" & ADDRESS(ROW()-27,Tabelle!$D$5+1,4,1)))",
  "repair:indirect_address_cross_sheet:=TRIMMEAN(INDIRECT(\"Spieler!\"&ADDRESS(ROW()-27,2,4,1)&\":\" & ADDRESS(ROW()-27,Tabelle!$D$5+1,4,1),1),1-(Einstellungen!$B$23/34))": "=TRIMMEAN(INDIRECT(\"$Spieler.\" & ADDRESS(ROW()-27,2,4,1)&\":\" & ADDRESS(ROW()-27,Tabelle!$D$5+1,4,1)),1-(Einstellungen!$B$23/34))",
  "repair:indirect_address_cross_sheet:=IF(MOD(STDEVP(INDIRECT(\"Spieler!\"&ADDRESS(ROW()-27,2,4,1)&\":\" & ADDRESS(ROW()-27,Tabelle!$D$5+1,4,1),1)),1)=0,STDEVP(INDIRECT(\"Spieler!\"&ADDRESS(ROW()-27,2,4,1)&\":\" & ADDRESS(ROW()-27,Tabelle!$D$5+1,4,1),1)),TEXT(STDEVP(INDIRECT(\"Spieler!\"&ADDRESS(ROW()-27,2,4,1)&\":\" & ADDRESS(ROW()-27,Tabelle!$D$5+1,4,1),1)),\"0,0#\"))": "=IF(MOD(STDEVP(INDIRECT(\"Spieler!\"&ADDRESS(ROW()-27,2,4,1)&\":\" & ADDRESS(ROW()-27,Tabelle!$D$5+1,4,1))),1)=0,STDEVP(INDIRECT(\"Spieler!\"&ADDRESS(ROW()-27,2,4,1)&\":\" & ADDRESS(ROW()-27,Tabelle!$D$5+1,4,1))),TEXT(STDEVP(INDIRECT(\"Spieler!\"&ADDRESS(ROW()-27,2,4,1)&\":\" & ADDRESS(ROW()-27,Tabelle!$D$5+1,4,1))),\"0,0#\"))",
  "repair:indirect_address_cross_sheet:=INDIRECT(ADDRESS(MATCH(SMALL(Spielplan!$C$2:$C$19,1),Spielplan!$C$2:$C$19,0)+1,2,3,,\"Spielplan\"),1)": "=INDIRECT(\"$Spielplan.\" & ADDRESS(MATCH(SMALL(Spielplan!$C$2:$C$19,1),Spielplan!$C$2:$C$19,0)+1,2,3),1)",
  "repair:indirect_address_cross_sheet:=INDIRECT(ADDRESS(SMALL(Spielplan!$C$2:$C$19,1)+1,2,3,,\"Spielplan\"),1)": "=INDIRECT(\"$Spielplan.\" & ADDRESS(SMALL(Spielplan!$C$2:$C$19,1)+1,2,3,))",
  "repair:indirect_address_cross_sheet:=INDIRECT(ADDRESS(MATCH(SMALL(Spielplan!$C$2:$C$19,2),Spielplan!$C$2:$C$19,0)+1,2,3,,\"Spielplan\"),1)": "=INDIRECT(\"$Spielplan.\" & ADDRESS(MATCH(SMALL(Spielplan!$C$2:$C$19,2),Spielplan!$C$2:$C$19,0)+1,2,3),1)",
  "repair:indirect_address_cross_sheet:=INDIRECT(ADDRESS(SMALL(Spielplan!$C$2:$C$19,2)+1,2,3,,\"Spielplan\"),1)": "=INDIRECT(\"$Spielplan.\" & ADDRESS(SMALL(Spielplan!$C$2:$C$19,2)+1,2,3,))",
  "repair:indirect_address_cross_sheet:=INDIRECT(ADDRESS(MATCH(SMALL(Spielplan!$C$2:$C$19,3),Spielplan!$C$2:$C$19,0)+1,2,3,,\"Spielplan\"),1)": "=INDIRECT(\"$Spielplan.\" & ADDRESS(MATCH(SMALL(Spielplan!$C$2:$C$19,3),Spielplan!$C$2:$C$19,0)+1,2,3))",
  "repair:indirect_address_cross_sheet:=INDIRECT(ADDRESS(SMALL(Spielplan!$C$2:$C$19,3)+1,2,3,,\"Spielplan\"),1)": "=INDIRECT(\"$Spielplan.\" & ADDRESS(SMALL(Spielplan!$C$2:$C$19,3)+1,2,3,),1)",
  "repair:indirect_address_cross_sheet:=INDIRECT(ADDRESS(MATCH(SMALL(Spielplan!$C$2:$C$19,4),Spielplan!$C$2:$C$19,0)+1,2,3,,\"Spielplan\"),1)": "=INDIRECT(\"$Spielplan.\" & ADDRESS(MATCH(SMALL(Spielplan!$C$2:$C$19,4),Spielplan!$C$2:$C$19,0)+1,2,3))",
  "repair:indirect_address_cross_sheet:=INDIRECT(ADDRESS(SMALL(Spielplan!$C$2:$C$19,4)+1,2,3,,\"Spielplan\"),1)": "=INDIRECT(\"$Spielplan.\" & ADDRESS(SMALL(Spielplan!$C$2:$C$19,4)+1,2,3,))",
  "repair:indirect_address_cross_sheet:=INDIRECT(ADDRESS(MATCH(SMALL(Spielplan!$C$2:$C$19,5),Spielplan!$C$2:$C$19,0)+1,2,3,,\"Spielplan\"),1)": "=INDIRECT(\"$Spielplan.\" & ADDRESS(MATCH(SMALL(Spielplan!$C$2:$C$19,5),Spielplan!$C$2:$C$19,0)+1,2,3),1)",
  "repair:indirect_address_cross_sheet:=INDIRECT(ADDRESS(SMALL(Spielplan!$C$2:$C$19,5)+1,2,3,,\"Spielplan\"),1)": "=INDIRECT(\"$Spielplan.\" & ADDRESS(SMALL(Spielplan!$C$2:$C$19,5)+1,2,3,),1)",
  "repair:indirect_address_cross_sheet:=INDIRECT(ADDRESS(MATCH(SMALL(Spielplan!$C$2:$C$19,6),Spielplan!$C$2:$C$19,0)+1,2,3,,\"Spielplan\"),1)": "=INDIRECT(\"$Spielplan.\" & ADDRESS(MATCH(SMALL(Spielplan!$C$2:$C$19,6),Spielplan!$C$2:$C$19,0)+1,2,3))",
  "repair:indirect_address_cross_sheet:=INDIRECT(ADDRESS(SMALL(Spielplan!$C$2:$C$19,6)+1,2,3,,\"Spielplan\"),1)": "=INDIRECT(\"$Spielplan.\" & ADDRESS(SMALL(Spielplan!$C$2:$C$19,6)+1,2,3,))",
  "repair:indirect_address_cross_sheet:=INDIRECT(ADDRESS(MATCH(SMALL(Spielplan!$C$2:$C$19,7),Spielplan!$C$2:$C$19,0)+1,2,3,,\"Spielplan\"),1)": "=INDIRECT(\"$Spielplan.\" & ADDRESS(MATCH(SMALL(Spielplan!$C$2:$C$19,7),Spielplan!$C$2:$C$19,0)+1,2,3),1)",
  "repair:indirect_address_cross_sheet:=INDIRECT(ADDRESS(SMALL(Spielplan!$C$2:$C$19,7)+1,2,3,,\"Spielplan\"),1)": "=INDIRECT(\"$Spielplan.\" & ADDRESS(SMALL(Spielplan!$C$2:$C$19,7)+1,2,3,))",
  "repair:indirect_address_cross_sheet:=INDIRECT(ADDRESS(MATCH(SMALL(Spielplan!$C$2:$C$19,8),Spielplan!$C$2:$C$19,0)+1,2,3,,\"Spielplan\"),1)": "=INDIRECT(\"$Spielplan.\" & ADDRESS(MATCH(SMALL(Spielplan!$C$2:$C$19,8),Spielplan!$C$2:$C$19,0)+1,2,3,))",
  "repair:indirect_address_cross_sheet:=INDIRECT(ADDRESS(SMALL(Spielplan!$C$2:$C$19,8)+1,2,3,,\"Spielplan\"),1)": "=INDIRECT(\"$Spielplan.\" & ADDRESS(SMALL(Spielplan!$C$2:$C$19,8)+1,2,3,))",
  "repair:indirect_address_cross_sheet:=INDIRECT(ADDRESS(MATCH(SMALL(Spielplan!$C$2:$C$19,9),Spielplan!$C$2:$C$19,0)+1,2,3,,\"Spielplan\"),1)": "=INDIRECT(\"$Spielplan.\" & ADDRESS(MATCH(SMALL(Spielplan!$C$2:$C$19,9),Spielplan!$C$2:$C$19,0)+1,2,3,))",
  "repair:indirect_address_cross_sheet:=INDIRECT(ADDRESS(SMALL(Spielplan!$C$2:$C$19,9)+1,2,3,,\"Spielplan\"),1)": "=INDIRECT(\"$Spielplan.\" & ADDRESS(SMALL(Spielplan!$C$2:$C$19,9)+1,2,3,))",
  "repair:indirect_address_cross_sheet:=INDIRECT(ADDRESS(MATCH(SMALL(Spielplan!$D$2:$D$19,1),Spielplan!$D$2:$D$19,0)+1,2,3,,\"Spielplan\"),1)": "=INDIRECT(\"$Spielplan.\" & ADDRESS(MATCH(SMALL(Spielplan!$D$2:$D$19,1),Spielplan!$D$2:$D$19,0)+1,2,3),1)",
  "repair:indirect_address_cross_sheet:=INDIRECT(ADDRESS(SMALL(Spielplan!$D$2:$D$19,1)+1,2,3,,\"Spielplan\"),1)": "=INDIRECT(\"$Spielplan.\" & ADDRESS(SMALL(Spielplan!$D$2:$D$19,1)+1,2,3,),1)",
  "repair:indirect_address_cross_sheet:=INDIRECT(ADDRESS(MATCH(SMALL(Spielplan!$D$2:$D$19,2),Spielplan!$D$2:$D$19,0)+1,2,3,,\"Spielplan\"),1)": "=INDIRECT(\"$Spielplan.\" & ADDRESS(MATCH(SMALL(Spielplan!$D$2:$D$19,2),Spielplan!$D$2:$D$19,0)+1,2,3),1)",
  "repair:indirect_address_cross_sheet:=INDIRECT(ADDRESS(SMALL(Spielplan!$D$2:$D$19,2)+1,2,3,,\"Spielplan\"),1)": "=INDIRECT(\"$Spielplan.\" & ADDRESS(SMALL(Spielplan!$D$2:$D$19,2)+1,2,3,))",
  "repair:indirect_address_cross_sheet:=INDIRECT(ADDRESS(MATCH(SMALL(Spielplan!$D$2:$D$19,3),Spielplan!$D$2:$D$19,0)+1,2,3,,\"Spielplan\"),1)": "=INDIRECT(\"$Spielplan.\" & ADDRESS(MATCH(SMALL(Spielplan!$D$2:$D$19,3),Spielplan!$D$2:$D$19,0)+1,2,3),1)",
  "repair:indirect_address_cross_sheet:=INDIRECT(ADDRESS(SMALL(Spielplan!$D$2:$D$19,3)+1,2,3,,\"Spielplan\"),1)": "=INDIRECT(\"$Spielplan.\" & ADDRESS(SMALL(Spielplan!$D$2:$D$19,3)+1,2,3,),1)",
  "repair:indirect_address_cross_sheet:=INDIRECT(ADDRESS(MATCH(SMALL(Spielplan!$D$2:$D$19,4),Spielplan!$D$2:$D$19,0)+1,2,3,,\"Spielplan\"),1)": "=INDIRECT(\"$Spielplan.\" & ADDRESS(MATCH(SMALL(Spielplan!$D$2:$D$19,4),Spielplan!$D$2:$D$19,0)+1,2,3),1)",
  "repair:indirect_address_cross_sheet:=INDIRECT(ADDRESS(SMALL(Spielplan!$D$2:$D$19,4)+1,2,3,,\"Spielplan\"),1)": "=INDIRECT(\"$Spielplan.\" & ADDRESS(SMALL(Spielplan!$D$2:$D$19,4)+1,2,3,))",
  "repair:indirect_address_cross_sheet:=INDIRECT(ADDRESS(MATCH(SMALL(Spielplan!$D$2:$D$19,5),Spielplan!$D$2:$D$19,0)+1,2,3,,\"Spielplan\"),1)": "=INDIRECT(\"$Spielplan.\" & ADDRESS(MATCH(SMALL(Spielplan!$D$2:$D$19,5),Spielplan!$D$2:$D$19,0)+1,2,3),1)",
  "repair:indirect_address_cross_sheet:=INDIRECT(ADDRESS(SMALL(Spielplan!$D$2:$D$19,5)+1,2,3,,\"Spielplan\"),1)": "=INDIRECT(\"$Spielplan.\" & ADDRESS(SMALL(Spielplan!$D$2:$D$19,5)+1,2,3,),1)",
  "repair:indirect_address_cross_sheet:=INDIRECT(ADDRESS(MATCH(SMALL(Spielplan!$D$2:$D$19,6),Spielplan!$D$2:$D$19,0)+1,2,3,,\"Spielplan\"),1)": "=INDIRECT(\"$Spielplan.\" & ADDRESS(MATCH(SMALL(Spielplan!$D$2:$D$19,6),Spielplan!$D$2:$D$19,0)+1,2,3),1)",
  "repair:indirect_address_cross_sheet:=INDIRECT(ADDRESS(SMALL(Spielplan!$D$2:$D$19,6)+1,2,3,,\"Spielplan\"),1)": "=INDIRECT(\"$Spielplan.\" & ADDRESS(SMALL(Spielplan!$D$2:$D$19,6)+1,2,3,),1)",
  "repair:indirect_address_cross_sheet:=INDIRECT(ADDRESS(MATCH(SMALL(Spielplan!$D$2:$D$19,7),Spielplan!$D$2:$D$19,0)+1,2,3,,\"Spielplan\"),1)": "=INDIRECT(\"$Spielplan.\" & ADDRESS(MATCH(SMALL(Spielplan!$D$2:$D$19,7),Spielplan!$D$2:$D$19,0)+1,2,3),1)",
  "repair:indirect_address_cross_sheet:=INDIRECT(ADDRESS(SMALL(Spielplan!$D$2:$D$19,7)+1,2,3,,\"Spielplan\"),1)": "=INDIRECT(\"$Spielplan.\" & ADDRESS(SMALL(Spielplan!$D$2:$D$19,7)+1,2,3,))",
  "repair:indirect_address_cross_sheet:=INDIRECT(ADDRESS(MATCH(SMALL(Spielplan!$D$2:$D$19,8),Spielplan!$D$2:$D$19,0)+1,2,3,,\"Spielplan\"),1)": "=INDIRECT(\"$Spielplan.\" & ADDRESS(MATCH(SMALL(Spielplan!$D$2:$D$19,8),Spielplan!$D$2:$D$19,0)+1,2,3),1)",
  "repair:indirect_address_cross_sheet:=INDIRECT(ADDRESS(SMALL(Spielplan!$D$2:$D$19,8)+1,2,3,,\"Spielplan\"),1)": "=INDIRECT(\"$Spielplan.\" & ADDRESS(SMALL(Spielplan!$D$2:$D$19,8)+1,2,3,))",
  "repair:indirect_address_cross_sheet:=INDIRECT(ADDRESS(MATCH(SMALL(Spielplan!$D$2:$D$19,9),Spielplan!$D$2:$D$19,0)+1,2,3,,\"Spielplan\"),1)": "=INDIRECT(\"$Spielplan.\" & ADDRESS(MATCH(SMALL(Spielplan!$D$2:$D$19,9),Spielplan!$D$2:$D$19,0)+1,2,3),1)",
  "repair:indirect_address_cross_sheet:=INDIRECT(ADDRESS(SMALL(Spielplan!$D$2:$D$19,9)+1,2,3,,\"Spielplan\"),1)": "=INDIRECT(\"$Spielplan.\" & ADDRESS(SMALL(Spielplan!$D$2:$D$19,9)+1,2,3,))",
  "repair:indirect_address_cross_sheet:=INDIRECT(ADDRESS(MATCH(SMALL(Spielplan!$E$2:$E$19,1),Spielplan!$E$2:$E$19,0)+1,2,3,,\"Spielplan\"),1)": "=INDIRECT(\"$Spielplan.\" & ADDRESS(MATCH(SMALL(Spielplan!$E$2:$E$19,1),Spielplan!$E$2:$E$19,0)+1,2,3),1)",
  "repair:indirect_address_cross_sheet:=INDIRECT(ADDRESS(SMALL(Spielplan!$E$2:$E$19,1)+1,2,3,,\"Spielplan\"),1)": "=INDIRECT(\"$Spielplan.\" & ADDRESS(SMALL(Spielplan!$E$2:$E$19,1)+1,2,3,))",
  "repair:indirect_address_cross_sheet:=INDIRECT(ADDRESS(MATCH(SMALL(Spielplan!$E$2:$E$19,2),Spielplan!$E$2:$E$19,0)+1,2,3,,\"Spielplan\"),1)": "=INDIRECT(\"$Spielplan.\" & ADDRESS(MATCH(SMALL(Spielplan!$E$2:$E$19,2),Spielplan!$E$2:$E$19,0)+1,2,3),1)",
  "repair:indirect_address_cross_sheet:=INDIRECT(ADDRESS(SMALL(Spielplan!$E$2:$E$19,2)+1,2,3,,\"Spielplan\"),1)": "=INDIRECT(\"$Spielplan.\" & ADDRESS(SMALL(Spielplan!$E$2:$E$19,2)+1,2,3,))",
  "repair:indirect_address_cross_sheet:=INDIRECT(ADDRESS(MATCH(SMALL(Spielplan!$E$2:$E$19,3),Spielplan!$E$2:$E$19,0)+1,2,3,,\"Spielplan\"),1)": "=INDIRECT(\"$Spielplan.\" & ADDRESS(MATCH(SMALL(Spielplan!$E$2:$E$19,3),Spielplan!$E$2:$E$19,0)+1,2,3),1)",
  "repair:indirect_address_cross_sheet:=INDIRECT(ADDRESS(SMALL(Spielplan!$E$2:$E$19,3)+1,2,3,,\"Spielplan\"),1)": "=INDIRECT(\"$Spielplan.\" & ADDRESS(SMALL(Spielplan!$E$2:$E$19,3)+1,2,3,))",
  "repair:indirect_address_cross_sheet:=INDIRECT(ADDRESS(MATCH(SMALL(Spielplan!$E$2:$E$19,4),Spielplan!$E$2:$E$19,0)+1,2,3,,\"Spielplan\"),1)": "=INDIRECT(\"$Spielplan.\" & ADDRESS(MATCH(SMALL(Spielplan!$E$2:$E$19,4),Spielplan!$E$2:$E$19,0)+1,2,3),1)",
  "repair:indirect_address_cross_sheet:=INDIRECT(ADDRESS(SMALL(Spielplan!$E$2:$E$19,4)+1,2,3,,\"Spielplan\"),1)": "=INDIRECT(\"$Spielplan.\" & ADDRESS(SMALL(Spielplan!$E$2:$E$19,4)+1,2,3,))",
  "repair:indirect_address_cross_sheet:=INDIRECT(ADDRESS(MATCH(SMALL(Spielplan!$E$2:$E$19,5),Spielplan!$E$2:$E$19,0)+1,2,3,,\"Spielplan\"),1)": "=INDIRECT(\"$Spielplan.\" & ADDRESS(MATCH(SMALL(Spielplan!$E$2:$E$19,5),Spielplan!$E$2:$E$19,0)+1,2,3),1)",
  "repair:indirect_address_cross_sheet:=INDIRECT(ADDRESS(SMALL(Spielplan!$E$2:$E$19,5)+1,2,3,,\"Spielplan\"),1)": "=INDIRECT(\"$Spielplan.\" & ADDRESS(SMALL(Spielplan!$E$2:$E$19,5)+1,2,3,),1)",
  "repair:indirect_address_cross_sheet:=INDIRECT(ADDRESS(MATCH(SMALL(Spielplan!$E$2:$E$19,6),Spielplan!$E$2:$E$19,0)+1,2,3,,\"Spielplan\"),1)": "=INDIRECT(\"$Spielplan.\" & ADDRESS(MATCH(SMALL(Spielplan!$E$2:$E$19,6),Spielplan!$E$2:$E$19,0)+1,2,3),1)",
  "repair:indirect_address_cross_sheet:=INDIRECT(ADDRESS(SMALL(Spielplan!$E$2:$E$19,6)+1,2,3,,\"Spielplan\"),1)": "=INDIRECT(\"$Spielplan.\" & ADDRESS(SMALL(Spielplan!$E$2:$E$19,6)+1,2,3,))",
  "repair:indirect_address_cross_sheet:=INDIRECT(ADDRESS(MATCH(SMALL(Spielplan!$E$2:$E$19,7),Spielplan!$E$2:$E$19,0)+1,2,3,,\"Spielplan\"),1)": "=INDIRECT(\"$Spielplan.\" & ADDRESS(MATCH(SMALL(Spielplan!$E$2:$E$19,7),Spielplan!$E$2:$E$19,0)+1,2,3),1)",
  "repair:indirect_address_cross_sheet:=INDIRECT(ADDRESS(SMALL(Spielplan!$E$2:$E$19,7)+1,2,3,,\"Spielplan\"),1)": "=INDIRECT(\"$Spielplan.\" & ADDRESS(SMALL(Spielplan!$E$2:$E$19,7)+1,2,3,))",
  "repair:indirect_address_cross_sheet:=INDIRECT(ADDRESS(MATCH(SMALL(Spielplan!$E$2:$E$19,8),Spielplan!$E$2:$E$19,0)+1,2,3,,\"Spielplan\"),1)": "=INDIRECT(\"$Spielplan.\" & ADDRESS(MATCH(SMALL(Spielplan!$E$2:$E$19,8),Spielplan!$E$2:$E$19,0)+1,2,3),1)",
  "repair:indirect_address_cross_sheet:=INDIRECT(ADDRESS(SMALL(Spielplan!$E$2:$E$19,8)+1,2,3,,\"Spielplan\"),1)": "=INDIRECT(\"$Spielplan.\" & ADDRESS(SMALL(Spielplan!$E$2:$E$19,8)+1,2,3,),1)",
  "repair:indirect_address_cross_sheet:=INDIRECT(ADDRESS(MATCH(SMALL(Spielplan!$E$2:$E$19,9),Spielplan!$E$2:$E$19,0)+1,2,3,,\"Spielplan\"),1)": "=INDIRECT(\"$Spielplan.\" & ADDRESS(MATCH(SMALL(Spielplan!$E$2:$E$19,9),Spielplan!$E$2:$E$19,0)+1,2,3),1)",
  "repair:indirect_address_cross_sheet:=INDIRECT(ADDRESS(SMALL(Spielplan!$E$2:$E$19,9)+1,2,3,,\"Spielplan\"),1)": "=INDIRECT(\"$Spielplan.\" & ADDRESS(SMALL(Spielplan!$E$2:$E$19,9)+1,2,3,))",
  "repair:indirect_address_cross_sheet:=INDIRECT(ADDRESS(MATCH(SMALL(Spielplan!$F$2:$F$19,1),Spielplan!$F$2:$F$19,0)+1,2,3,,\"Spielplan\"),1)": "=INDIRECT(\"$Spielplan.\" & ADDRESS(MATCH(SMALL(Spielplan!$F$2:$F$19,1),Spielplan!$F$2:$F$19,0)+1,2,3),1)",
  "repair:indirect_address_cross_sheet:=INDIRECT(ADDRESS(SMALL(Spielplan!$F$2:$F$19,1)+1,2,3,,\"Spielplan\"),1)": "=INDIRECT(\"$Spielplan.\" & ADDRESS(SMALL(Spielplan!$F$2:$F$19,1)+1,2,3,))",
  "repair:indirect_address_cross_sheet:=INDIRECT(ADDRESS(MATCH(SMALL(Spielplan!$F$2:$F$19,2),Spielplan!$F$2:$F$19,0)+1,2,3,,\"Spielplan\"),1)": "=INDIRECT(\"$Spielplan.\" & ADDRESS(MATCH(SMALL(Spielplan!$F$2:$F$19,2),Spielplan!$F$2:$F$19,0)+1,2,3),1)",
  "repair:indirect_address_cross_sheet:=INDIRECT(ADDRESS(SMALL(Spielplan!$F$2:$F$19,2)+1,2,3,,\"Spielplan\"),1)": "=INDIRECT(\"$Spielplan.\" & ADDRESS(SMALL(Spielplan!$F$2:$F$19,2)+1,2,3,))",
  "repair:indirect_address_cross_sheet:=INDIRECT(ADDRESS(MATCH(SMALL(Spielplan!$F$2:$F$19,3),Spielplan!$F$2:$F$19,0)+1,2,3,,\"Spielplan\"),1)": "=INDIRECT(\"$Spielplan.\" & ADDRESS(MATCH(SMALL(Spielplan!$F$2:$F$19,3),Spielplan!$F$2:$F$19,0)+1,2,3),1)",
  "repair:indirect_address_cross_sheet:=INDIRECT(ADDRESS(SMALL(Spielplan!$F$2:$F$19,3)+1,2,3,,\"Spielplan\"),1)": "=INDIRECT(\"$Spielplan.\" & ADDRESS(SMALL(Spielplan!$F$2:$F$19,3)+1,2,3,),1)",
  "repair:indirect_address_cross_sheet:=INDIRECT(ADDRESS(MATCH(SMALL(Spielplan!$F$2:$F$19,4),Spielplan!$F$2:$F$19,0)+1,2,3,,\"Spielplan\"),1)": "=INDIRECT(\"$Spielplan.\" & ADDRESS(MATCH(SMALL(Spielplan!$F$2:$F$19,4),Spielplan!$F$2:$F$19,0)+1,2,3),1)",
  "repair:indirect_address_cross_sheet:=INDIRECT(ADDRESS(SMALL(Spielplan!$F$2:$F$19,4)+1,2,3,,\"Spielplan\"),1)": "=INDIRECT(\"$Spielplan.\" & ADDRESS(SMALL(Spielplan!$F$2:$F$19,4)+1,2,3,),1)",
  "repair:indirect_address_cross_sheet:=INDIRECT(ADDRESS(MATCH(SMALL(Spielplan!$F$2:$F$19,5),Spielplan!$F$2:$F$19,0)+1,2,3,,\"Spielplan\"),1)": "=INDIRECT(\"$Spielplan.\" & ADDRESS(MATCH(SMALL(Spielplan!$F$2:$F$19,5),Spielplan!$F$2:$F$19,0)+1,2,3,),1)",
  "repair:indirect_address_cross_sheet:=INDIRECT(ADDRESS(SMALL(Spielplan!$F$2:$F$19,5)+1,2,3,,\"Spielplan\"),1)": "=INDIRECT(\"$Spielplan.\" & ADDRESS(SMALL(Spielplan!$F$2:$F$19,5)+1,2,3,),1)",
  "repair:indirect_address_cross_sheet:=INDIRECT(ADDRESS(MATCH(SMALL(Spielplan!$F$2:$F$19,6),Spielplan!$F$2:$F$19,0)+1,2,3,,\"Spielplan\"),1)": "=INDIRECT(\"$Spielplan.\" & ADDRESS(MATCH(SMALL(Spielplan!$F$2:$F$19,6),Spielplan!$F$2:$F$19,0)+1,2,3,))",
  "repair:indirect_address_cross_sheet:=INDIRECT(ADDRESS(SMALL(Spielplan!$F$2:$F$19,6)+1,2,3,,\"Spielplan\"),1)": "=INDIRECT(\"$Spielplan.\" & ADDRESS(SMALL(Spielplan!$F$2:$F$19,6)+1,2,3,))",
  "repair:indirect_address_cross_sheet:=INDIRECT(ADDRESS(MATCH(SMALL(Spielplan!$F$2:$F$19,7),Spielplan!$F$2:$F$19,0)+1,2,3,,\"Spielplan\"),1)": "=INDIRECT(\"$Spielplan.\" & ADDRESS(MATCH(SMALL(Spielplan!$F$2:$F$19,7),Spielplan!$F$2:$F$19,0)+1,2,3),1)",
  "repair:indirect_address_cross_sheet:=INDIRECT(ADDRESS(SMALL(Spielplan!$F$2:$F$19,7)+1,2,3,,\"Spielplan\"),1)": "=INDIRECT(\"$Spielplan.\" & ADDRESS(SMALL(Spielplan!$F$2:$F$19,7)+1,2,3,))",
  "repair:indirect_address_cross_sheet:=INDIRECT(ADDRESS(MATCH(SMALL(Spielplan!$F$2:$F$19,8),Spielplan!$F$2:$F$19,0)+1,2,3,,\"Spielplan\"),1)": "=INDIRECT(\"$Spielplan.\" & ADDRESS(MATCH(SMALL(Spielplan!$F$2:$F$19,8),Spielplan!$F$2:$F$19,0)+1,2,3),1)",
  "repair:indirect_address_cross_sheet:=INDIRECT(ADDRESS(SMALL(Spielplan!$F$2:$F$19,8)+1,2,3,,\"Spielplan\"),1)": "=INDIRECT(\"$Spielplan.\" & ADDRESS(SMALL(Spielplan!$F$2:$F$19,8)+1,2,3,))",
  "repair:indirect_address_cross_sheet:=INDIRECT(ADDRESS(MATCH(SMALL(Spielplan!$F$2:$F$19,9),Spielplan!$F$2:$F$19,0)+1,2,3,,\"Spielplan\"),1)": "=INDIRECT(\"$Spielplan.\" & ADDRESS(MATCH(SMALL(Spielplan!$F$2:$F$19,9),Spielplan!$F$2:$F$19,0)+1,2,3),1)",
  "repair:indirect_address_cross_sheet:=INDIRECT(ADDRESS(SMALL(Spielplan!$F$2:$F$19,9)+1,2,3,,\"Spielplan\"),1)": "=INDIRECT(\"$Spielplan.\" & ADDRESS(SMALL(Spielplan!$F$2:$F$19,9)+1,2,3,),1)",
  "repair:indirect_address_cross_sheet:=INDIRECT(ADDRESS(MATCH(SMALL(Spielplan!$G$2:$G$19,1),Spielplan!$G$2:$G$19,0)+1,2,3,,\"Spielplan\"),1)": "=INDIRECT(\"$Spielplan.\" & ADDRESS(MATCH(SMALL(Spielplan!$G$2:$G$19,1),Spielplan!$G$2:$G$19,0)+1,2,3),1)",
  "repair:indirect_address_cross_sheet:=INDIRECT(ADDRESS(SMALL(Spielplan!$G$2:$G$19,1)+1,2,3,,\"Spielplan\"),1)": "=INDIRECT(\"$Spielplan.\" & ADDRESS(SMALL(Spielplan!$G$2:$G$19,1)+1,2,3,),1)",
  "repair:indirect_address_cross_sheet:=INDIRECT(ADDRESS(MATCH(SMALL(Spielplan!$G$2:$G$19,2),Spielplan!$G$2:$G$19,0)+1,2,3,,\"Spielplan\"),1)": "=INDIRECT(\"$Spielplan.\" & ADDRESS(MATCH(SMALL(Spielplan!$G$2:$G$19,2),Spielplan!$G$2:$G$19,0)+1,2,3),1)",
  "repair:indirect_address_cross_sheet:=INDIRECT(ADDRESS(SMALL(Spielplan!$G$2:$G$19,2)+1,2,3,,\"Spielplan\"),1)": "=INDIRECT(\"$Spielplan.\" & ADDRESS(SMALL(Spielplan!$G$2:$G$19,2)+1,2,3,))",
  "repair:indirect_address_cross_sheet:=INDIRECT(ADDRESS(MATCH(SMALL(Spielplan!$G$2:$G$19,3),Spielplan!$G$2:$G$19,0)+1,2,3,,\"Spielplan\"),1)": "=INDIRECT(\"$Spielplan.\" & ADDRESS(MATCH(SMALL(Spielplan!$G$2:$G$19,3),Spielplan!$G$2:$G$19,0)+1,2,3),1)",
  "repair:indirect_address_cross_sheet:=INDIRECT(ADDRESS(SMALL(Spielplan!$G$2:$G$19,3)+1,2,3,,\"Spielplan\"),1)": "=INDIRECT(\"$Spielplan.\" & ADDRESS(SMALL(Spielplan!$G$2:$G$19,3)+1,2,3,),1)",
  "repair:indirect_address_cross_sheet:=INDIRECT(ADDRESS(MATCH(SMALL(Spielplan!$G$2:$G$19,4),Spielplan!$G$2:$G$19,0)+1,2,3,,\"Spielplan\"),1)": "=INDIRECT(\"$Spielplan.\" & ADDRESS(MATCH(SMALL(Spielplan!$G$2:$G$19,4),Spielplan!$G$2:$G$19,0)+1,2,3),1)",
  "repair:indirect_address_cross_sheet:=INDIRECT(ADDRESS(SMALL(Spielplan!$G$2:$G$19,4)+1,2,3,,\"Spielplan\"),1)": "=INDIRECT(\"$Spielplan.\" & ADDRESS(SMALL(Spielplan!$G$2:$G$19,4)+1,2,3,),1)",
  "repair:indirect_address_cross_sheet:=INDIRECT(ADDRESS(MATCH(SMALL(Spielplan!$G$2:$G$19,5),Spielplan!$G$2:$G$19,0)+1,2,3,,\"Spielplan\"),1)": "=INDIRECT(\"$Spielplan.\" & ADDRESS(MATCH(SMALL(Spielplan!$G$2:$G$19,5),Spielplan!$G$2:$G$19,0)+1,2,3),1)",
  "repair:indirect_address_cross_sheet:=INDIRECT(ADDRESS(SMALL(Spielplan!$G$2:$G$19,5)+1,2,3,,\"Spielplan\"),1)": "=INDIRECT(\"$Spielplan.\" & ADDRESS(SMALL(Spielplan!$G$2:$G$19,5)+1,2,3,),1)",
  "repair:indirect_address_cross_sheet:=INDIRECT(ADDRESS(MATCH(SMALL(Spielplan!$G$2:$G$19,6),Spielplan!$G$2:$G$19,0)+1,2,3,,\"Spielplan\"),1)": "=INDIRECT(\"$Spielplan.\" & ADDRESS(MATCH(SMALL(Spielplan!$G$2:$G$19,6),Spielplan!$G$2:$G$19,0)+1,2,3),1)",
  "repair:indirect_address_cross_sheet:=INDIRECT(ADDRESS(SMALL(Spielplan!$G$2:$G$19,6)+1,2,3,,\"Spielplan\"),1)": "=INDIRECT(\"$Spielplan.\" & ADDRESS(SMALL(Spielplan!$G$2:$G$19,6)+1,2,3,))",
  "repair:indirect_address_cross_sheet:=INDIRECT(ADDRESS(MATCH(SMALL(Spielplan!$G$2:$G$19,7),Spielplan!$G$2:$G$19,0)+1,2,3,,\"Spielplan\"),1)": "=INDIRECT(\"$Spielplan.\" & ADDRESS(MATCH(SMALL(Spielplan!$G$2:$G$19,7),Spielplan!$G$2:$G$19,0)+1,2,3),1)",
  "repair:indirect_address_cross_sheet:=INDIRECT(ADDRESS(SMALL(Spielplan!$G$2:$G$19,7)+1,2,3,,\"Spielplan\"),1)": "=INDIRECT(\"$Spielplan.\" & ADDRESS(SMALL(Spielplan!$G$2:$G$19,7)+1,2,3,))",
  "repair:indirect_address_cross_sheet:=INDIRECT(ADDRESS(MATCH(SMALL(Spielplan!$G$2:$G$19,8),Spielplan!$G$2:$G$19,0)+1,2,3,,\"Spielplan\"),1)": "=INDIRECT(\"$Spielplan.\" & ADDRESS(MATCH(SMALL(Spielplan!$G$2:$G$19,8),Spielplan!$G$2:$G$19,0)+1,2,3),1)",
  "repair:indirect_address_cross_sheet:=INDIRECT(ADDRESS(SMALL(Spielplan!$G$2:$G$19,8)+1,2,3,,\"Spielplan\"),1)": "=INDIRECT(\"$Spielplan.\" & ADDRESS(SMALL(Spielplan!$G$2:$G$19,8)+1,2,3,),1)",
  "repair:indirect_address_cross_sheet:=INDIRECT(ADDRESS(MATCH(SMALL(Spielplan!$G$2:$G$19,9),Spielplan!$G$2:$G$19,0)+1,2,3,,\"Spielplan\"),1)": "=INDIRECT(\"$Spielplan.\" & ADDRESS(MATCH(SMALL(Spielplan!$G$2:$G$19,9),Spielplan!$G$2:$G$19,0)+1,2,3),1)",
  "repair:indirect_address_cross_sheet:=INDIRECT(ADDRESS(SMALL(Spielplan!$G$2:$G$19,9)+1,2,3,,\"Spielplan\"),1)": "=INDIRECT(\"$Spielplan.\" & ADDRESS(SMALL(Spielplan!$G$2:$G$19,9)+1,2,3,),1)",
  "repair:indirect_address_cross_sheet:=INDIRECT(ADDRESS(MATCH(SMALL(Spielplan!$H$2:$H$19,1),Spielplan!$H$2:$H$19,0)+1,2,3,,\"Spielplan\"),1)": "=INDIRECT(\"$Spielplan.\" & ADDRESS(MATCH(SMALL(Spielplan!$H$2:$H$19,1),Spielplan!$H$2:$H$19,0)+1,2,3),1)",
  "repair:indirect_address_cross_sheet:=INDIRECT(ADDRESS(SMALL(Spielplan!$H$2:$H$19,1)+1,2,3,,\"Spielplan\"),1)": "=INDIRECT(\"$Spielplan.\" & ADDRESS(SMALL(Spielplan!$H$2:$H$19,1)+1,2,3,))",
  "repair:indirect_address_cross_sheet:=INDIRECT(ADDRESS(MATCH(SMALL(Spielplan!$H$2:$H$19,2),Spielplan!$H$2:$H$19,0)+1,2,3,,\"Spielplan\"),1)": "=INDIRECT(\"$Spielplan.\" & ADDRESS(MATCH(SMALL(Spielplan!$H$2:$H$19,2),Spielplan!$H$2:$H$19,0)+1,2,3),1)",
  "repair:indirect_address_cross_sheet:=INDIRECT(ADDRESS(SMALL(Spielplan!$H$2:$H$19,2)+1,2,3,,\"Spielplan\"),1)": "=INDIRECT(\"$Spielplan.\" & ADDRESS(SMALL(Spielplan!$H$2:$H$19,2)+1,2,3,))",
  "repair:indirect_address_cross_sheet:=INDIRECT(ADDRESS(MATCH(SMALL(Spielplan!$H$2:$H$19,3),Spielplan!$H$2:$H$19,0)+1,2,3,,\"Spielplan\"),1)": "=INDIRECT(\"$Spielplan.\" & ADDRESS(MATCH(SMALL(Spielplan!$H$2:$H$19,3),Spielplan!$H$2:$H$19,0)+1,2,3),1)",
  "repair:indirect_address_cross_sheet:=INDIRECT(ADDRESS(SMALL(Spielplan!$H$2:$H$19,3)+1,2,3,,\"Spielplan\"),1)": "=INDIRECT(\"$Spielplan.\" & ADDRESS(SMALL(Spielplan!$H$2:$H$19,3)+1,2,3,))",
  "repair:indirect_address_cross_sheet:=INDIRECT(ADDRESS(MATCH(SMALL(Spielplan!$H$2:$H$19,4),Spielplan!$H$2:$H$19,0)+1,2,3,,\"Spielplan\"),1)": "=INDIRECT(\"$Spielplan.\" & ADDRESS(MATCH(SMALL(Spielplan!$H$2:$H$19,4),Spielplan!$H$2:$H$19,0)+1,2,3),1)",
  "repair:indirect_address_cross_sheet:=INDIRECT(ADDRESS(SMALL(Spielplan!$H$2:$H$19,4)+1,2,3,,\"Spielplan\"),1)": "=INDIRECT(\"$Spielplan.\" & ADDRESS(SMALL(Spielplan!$H$2:$H$19,4)+1,2,3,))",
  "repair:indirect_address_cross_sheet:=INDIRECT(ADDRESS(MATCH(SMALL(Spielplan!$H$2:$H$19,5),Spielplan!$H$2:$H$19,0)+1,2,3,,\"Spielplan\"),1)": "=INDIRECT(\"$Spielplan.\" & ADDRESS(MATCH(SMALL(Spielplan!$H$2:$H$19,5),Spielplan!$H$2:$H$19,0)+1,2,3),1)",
  "repair:indirect_address_cross_sheet:=INDIRECT(ADDRESS(SMALL(Spielplan!$H$2:$H$19,5)+1,2,3,,\"Spielplan\"),1)": "=INDIRECT(\"$Spielplan.\" & ADDRESS(SMALL(Spielplan!$H$2:$H$19,5)+1,2,3,),1)",
  "repair:indirect_address_cross_sheet:=INDIRECT(ADDRESS(MATCH(SMALL(Spielplan!$H$2:$H$19,6),Spielplan!$H$2:$H$19,0)+1,2,3,,\"Spielplan\"),1)": "=INDIRECT(\"$Spielplan.\" & ADDRESS(MATCH(SMALL(Spielplan!$H$2:$H$19,6),Spielplan!$H$2:$H$19,0)+1,2,3),1)",
  "repair:indirect_address_cross_sheet:=INDIRECT(ADDRESS(SMALL(Spielplan!$H$2:$H$19,6)+1,2,3,,\"Spielplan\"),1)": "=INDIRECT(\"$Spielplan.\" & ADDRESS(SMALL(Spielplan!$H$2:$H$19,6)+1,2,3,))",
  "repair:indirect_address_cross_sheet:=INDIRECT(ADDRESS(MATCH(SMALL(Spielplan!$H$2:$H$19,7),Spielplan!$H$2:$H$19,0)+1,2,3,,\"Spielplan\"),1)": "=INDIRECT(\"$Spielplan.\" & ADDRESS(MATCH(SMALL(Spielplan!$H$2:$H$19,7),Spielplan!$H$2:$H$19,0)+1,2,3),1)",
  "repair:indirect_address_cross_sheet:=INDIRECT(ADDRESS(SMALL(Spielplan!$H$2:$H$19,7)+1,2,3,,\"Spielplan\"),1)": "=INDIRECT(\"$Spielplan.\" & ADDRESS(SMALL(Spielplan!$H$2:$H$19,7)+1,2,3,))",
  "repair:indirect_address_cross_sheet:=INDIRECT(ADDRESS(MATCH(SMALL(Spielplan!$H$2:$H$19,8),Spielplan!$H$2:$H$19,0)+1,2,3,,\"Spielplan\"),1)": "=INDIRECT(\"$Spielplan.\" & ADDRESS(MATCH(SMALL(Spielplan!$H$2:$H$19,8),Spielplan!$H$2:$H$19,0)+1,2,3),1)",
  "repair:indirect_address_cross_sheet:=INDIRECT(ADDRESS(SMALL(Spielplan!$H$2:$H$19,8)+1,2,3,,\"Spielplan\"),1)": "=INDIRECT(\"$Spielplan.\" & ADDRESS(SMALL(Spielplan!$H$2:$H$19,8)+1,2,3,))",
  "repair:indirect_address_cross_sheet:=INDIRECT(ADDRESS(MATCH(SMALL(Spielplan!$H$2:$H$19,9),Spielplan!$H$2:$H$19,0)+1,2,3,,\"Spielplan\"),1)": "=INDIRECT(\"$Spielplan.\" & ADDRESS(MATCH(SMALL(Spielplan!$H$2:$H$19,9),Spielplan!$H$2:$H$19,0)+1,2,3),1)",
  "repair:indirect_address_cross_sheet:=INDIRECT(ADDRESS(SMALL(Spielplan!$H$2:$H$19,9)+1,2,3,,\"Spielplan\"),1)": "=INDIRECT(\"$Spielplan.\" & ADDRESS(SMALL(Spielplan!$H$2:$H$19,9)+1,2,3,))",
  "repair:indirect_address_cross_sheet:=INDIRECT(ADDRESS(MATCH(SMALL(Spielplan!$I$2:$I$19,1),Spielplan!$I$2:$I$19,0)+1,2,3,,\"Spielplan\"),1)": "=INDIRECT(\"$Spielplan.\" & ADDRESS(MATCH(SMALL(Spielplan!$I$2:$I$19,1),Spielplan!$I$2:$I$19,0)+1,2,3),1)",
  "repair:indirect_address_cross_sheet:=INDIRECT(ADDRESS(SMALL(Spielplan!$I$2:$I$19,1)+1,2,3,,\"Spielplan\"),1)": "=INDIRECT(\"$Spielplan.\" & ADDRESS(SMALL(Spielplan!$I$2:$I$19,1)+1,2,3,))",
  "repair:indirect_address_cross_sheet:=INDIRECT(ADDRESS(MATCH(SMALL(Spielplan!$I$2:$I$19,2),Spielplan!$I$2:$I$19,0)+1,2,3,,\"Spielplan\"),1)": "=INDIRECT(\"$Spielplan.\" & ADDRESS(MATCH(SMALL(Spielplan!$I$2:$I$19,2),Spielplan!$I$2:$I$19,0)+1,2,3),1)",
  "repair:indirect_address_cross_sheet:=INDIRECT(ADDRESS(SMALL(Spielplan!$I$2:$I$19,2)+1,2,3,,\"Spielplan\"),1)": "=INDIRECT(\"$Spielplan.\" & ADDRESS(SMALL(Spielplan!$I$2:$I$19,2)+1,2,3,),1)",
  "repair:indirect_address_cross_sheet:=INDIRECT(ADDRESS(MATCH(SMALL(Spielplan!$I$2:$I$19,3),Spielplan!$I$2:$I$19,0)+1,2,3,,\"Spielplan\"),1)": "=INDIRECT(\"$Spielplan.\" & ADDRESS(MATCH(SMALL(Spielplan!$I$2:$I$19,3),Spielplan!$I$2:$I$19,0)+1,2,3),1)",
  "repair:indirect_address_cross_sheet:=INDIRECT(ADDRESS(SMALL(Spielplan!$I$2:$I$19,3)+1,2,3,,\"Spielplan\"),1)": "=INDIRECT(\"$Spielplan.\" & ADDRESS(SMALL(Spielplan!$I$2:$I$19,3)+1,2,3,),1)",
  "repair:indirect_address_cross_sheet:=INDIRECT(ADDRESS(MATCH(SMALL(Spielplan!$I$2:$I$19,4),Spielplan!$I$2:$I$19,0)+1,2,3,,\"Spielplan\"),1)": "=INDIRECT(\"$Spielplan.\" & ADDRESS(MATCH(SMALL(Spielplan!$I$2:$I$19,4),Spielplan!$I$2:$I$19,0)+1,2,3),1)",
  "repair:indirect_address_cross_sheet:=INDIRECT(ADDRESS(SMALL(Spielplan!$I$2:$I$19,4)+1,2,3,,\"Spielplan\"),1)": "=INDIRECT(\"$Spielplan.\" & ADDRESS(SMALL(Spielplan!$I$2:$I$19,4)+1,2,3,))",
  "repair:indirect_address_cross_sheet:=INDIRECT(ADDRESS(MATCH(SMALL(Spielplan!$I$2:$I$19,5),Spielplan!$I$2:$I$19,0)+1,2,3,,\"Spielplan\"),1)": "=INDIRECT(\"$Spielplan.\" & ADDRESS(MATCH(SMALL(Spielplan!$I$2:$I$19,5),Spielplan!$I$2:$I$19,0)+1,2,3))",
  "repair:indirect_address_cross_sheet:=INDIRECT(ADDRESS(SMALL(Spielplan!$I$2:$I$19,5)+1,2,3,,\"Spielplan\"),1)": "=INDIRECT(\"$Spielplan.\" & ADDRESS(SMALL(Spielplan!$I$2:$I$19,5)+1,2,3,),1)",
  "repair:indirect_address_cross_sheet:=INDIRECT(ADDRESS(MATCH(SMALL(Spielplan!$I$2:$I$19,6),Spielplan!$I$2:$I$19,0)+1,2,3,,\"Spielplan\"),1)": "=INDIRECT(\"$Spielplan.\" & ADDRESS(MATCH(SMALL(Spielplan!$I$2:$I$19,6),Spielplan!$I$2:$I$19,0)+1,2,3))",
  "repair:indirect_address_cross_sheet:=INDIRECT(ADDRESS(SMALL(Spielplan!$I$2:$I$19,6)+1,2,3,,\"Spielplan\"),1)": "=INDIRECT(\"$Spielplan.\" & ADDRESS(SMALL(Spielplan!$I$2:$I$19,6)+1,2,3,),1)",
  "repair:indirect_address_cross_sheet:=INDIRECT(ADDRESS(MATCH(SMALL(Spielplan!$I$2:$I$19,7),Spielplan!$I$2:$I$19,0)+1,2,3,,\"Spielplan\"),1)": "=INDIRECT(\"$Spielplan.\" & ADDRESS(MATCH(SMALL(Spielplan!$I$2:$I$19,7),Spielplan!$I$2:$I$19,0)+1,2,3))",
  "repair:indirect_address_cross_sheet:=INDIRECT(ADDRESS(SMALL(Spielplan!$I$2:$I$19,7)+1,2,3,,\"Spielplan\"),1)": "=INDIRECT(\"$Spielplan.\" & ADDRESS(SMALL(Spielplan!$I$2:$I$19,7)+1,2,3,))",
  "repair:indirect_address_cross_sheet:=INDIRECT(ADDRESS(MATCH(SMALL(Spielplan!$I$2:$I$19,8),Spielplan!$I$2:$I$19,0)+1,2,3,,\"Spielplan\"),1)": "=INDIRECT(\"$Spielplan.\" & ADDRESS(MATCH(SMALL(Spielplan!$I$2:$I$19,8),Spielplan!$I$2:$I$19,0)+1,2,3),1)",
  "repair:indirect_address_cross_sheet:=INDIRECT(ADDRESS(SMALL(Spielplan!$I$2:$I$19,8)+1,2,3,,\"Spielplan\"),1)": "=INDIRECT(\"$Spielplan.\" & ADDRESS(SMALL(Spielplan!$I$2:$I$19,8)+1,2,3,))",
  "repair:indirect_address_cross_sheet:=INDIRECT(ADDRESS(MATCH(SMALL(Spielplan!$I$2:$I$19,9),Spielplan!$I$2:$I$19,0)+1,2,3,,\"Spielplan\"),1)": "=INDIRECT(\"$Spielplan.\" & ADDRESS(MATCH(SMALL(Spielplan!$I$2:$I$19,9),Spielplan!$I$2:$I$19,0)+1,2,3),1)",
  "repair:indirect_address_cross_sheet:=INDIRECT(ADDRESS(SMALL(Spielplan!$I$2:$I$19,9)+1,2,3,,\"Spielplan\"),1)": "=INDIRECT(\"$Spielplan.\" & ADDRESS(SMALL(Spielplan!$I$2:$I$19,9)+1,2,3,))",
  "repair:indirect_address_cross_sheet:=INDIRECT(ADDRESS(MATCH(SMALL(Spielplan!$J$2:$J$19,1),Spielplan!$J$2:$J$19,0)+1,2,3,,\"Spielplan\"),1)": "=INDIRECT(\"$Spielplan.\" & ADDRESS(MATCH(SMALL(Spielplan!$J$2:$J$19,1),Spielplan!$J$2:$J$19,0)+1,2,3),1)",
  "repair:indirect_address_cross_sheet:=INDIRECT(ADDRESS(SMALL(Spielplan!$J$2:$J$19,1)+1,2,3,,\"Spielplan\"),1)": "=INDIRECT(\"$Spielplan.\" & ADDRESS(SMALL(Spielplan!$J$2:$J$19,1)+1,2,3,),1)",
  "repair:indirect_address_cross_sheet:=INDIRECT(ADDRESS(MATCH(SMALL(Spielplan!$J$2:$J$19,2),Spielplan!$J$2:$J$19,0)+1,2,3,,\"Spielplan\"),1)": "=INDIRECT(\"$Spielplan.\" & ADDRESS(MATCH(SMALL(Spielplan!$J$2:$J$19,2),Spielplan!$J$2:$J$19,0)+1,2,3),1)",
  "repair:indirect_address_cross_sheet:=INDIRECT(ADDRESS(SMALL(Spielplan!$J$2:$J$19,2)+1,2,3,,\"Spielplan\"),1)": "=INDIRECT(\"$Spielplan.\" & ADDRESS(SMALL(Spielplan!$J$2:$J$19,2)+1,2,3,),1)",
  "repair:indirect_address_cross_sheet:=INDIRECT(ADDRESS(MATCH(SMALL(Spielplan!$J$2:$J$19,3),Spielplan!$J$2:$J$19,0)+1,2,3,,\"Spielplan\"),1)": "=INDIRECT(\"$Spielplan.\" & ADDRESS(MATCH(SMALL(Spielplan!$J$2:$J$19,3),Spielplan!$J$2:$J$19,0)+1,2,3),1)",
  "repair:indirect_address_cross_sheet:=INDIRECT(ADDRESS(SMALL(Spielplan!$J$2:$J$19,3)+1,2,3,,\"Spielplan\"),1)": "=INDIRECT(\"$Spielplan.\" & ADDRESS(SMALL(Spielplan!$J$2:$J$19,3)+1,2,3,),1)",
  "repair:indirect_address_cross_sheet:=INDIRECT(ADDRESS(MATCH(SMALL(Spielplan!$J$2:$J$19,4),Spielplan!$J$2:$J$19,0)+1,2,3,,\"Spielplan\"),1)": "=INDIRECT(\"$Spielplan.\" & ADDRESS(MATCH(SMALL(Spielplan!$J$2:$J$19,4),Spielplan!$J$2:$J$19,0)+1,2,3),1)",
  "repair:indirect_address_cross_sheet:=INDIRECT(ADDRESS(SMALL(Spielplan!$J$2:$J$19,4)+1,2,3,,\"Spielplan\"),1)": "=INDIRECT(\"$Spielplan.\" & ADDRESS(SMALL(Spielplan!$J$2:$J$19,4)+1,2,3,),1)",
  "repair:indirect_address_cross_sheet:=INDIRECT(ADDRESS(MATCH(SMALL(Spielplan!$J$2:$J$19,5),Spielplan!$J$2:$J$19,0)+1,2,3,,\"Spielplan\"),1)": "=INDIRECT(\"$Spielplan.\" & ADDRESS(MATCH(SMALL(Spielplan!$J$2:$J$19,5),Spielplan!$J$2:$J$19,0)+1,2,3),1)",
  "repair:indirect_address_cross_sheet:=INDIRECT(ADDRESS(SMALL(Spielplan!$J$2:$J$19,5)+1,2,3,,\"Spielplan\"),1)": "=INDIRECT(\"$Spielplan.\" & ADDRESS(SMALL(Spielplan!$J$2:$J$19,5)+1,2,3,))",
  "repair:indirect_address_cross_sheet:=INDIRECT(ADDRESS(MATCH(SMALL(Spielplan!$J$2:$J$19,6),Spielplan!$J$2:$J$19,0)+1,2,3,,\"Spielplan\"),1)": "=INDIRECT(\"$Spielplan.\" & ADDRESS(MATCH(SMALL(Spielplan!$J$2:$J$19,6),Spielplan!$J$2:$J$19,0)+1,2,3),1)",
  "repair:indirect_address_cross_sheet:=INDIRECT(ADDRESS(SMALL(Spielplan!$J$2:$J$19,6)+1,2,3,,\"Spielplan\"),1)": "=INDIRECT(\"$Spielplan.\" & ADDRESS(SMALL(Spielplan!$J$2:$J$19,6)+1,2,3,))",
  "repair:indirect_address_cross_sheet:=INDIRECT(ADDRESS(MATCH(SMALL(Spielplan!$J$2:$J$19,7),Spielplan!$J$2:$J$19,0)+1,2,3,,\"Spielplan\"),1)": "=INDIRECT(\"$Spielplan.\" & ADDRESS(MATCH(SMALL(Spielplan!$J$2:$J$19,7),Spielplan!$J$2:$J$19,0)+1,2,3),1)",
  "repair:indirect_address_cross_sheet:=INDIRECT(ADDRESS(SMALL(Spielplan!$J$2:$J$19,7)+1,2,3,,\"Spielplan\"),1)": "=INDIRECT(\"$Spielplan.\" & ADDRESS(SMALL(Spielplan!$J$2:$J$19,7)+1,2,3,),1)",
  "repair:indirect_address_cross_sheet:=INDIRECT(ADDRESS(MATCH(SMALL(Spielplan!$J$2:$J$19,8),Spielplan!$J$2:$J$19,0)+1,2,3,,\"Spielplan\"),1)": "=INDIRECT(\"$Spielplan.\" & ADDRESS(MATCH(SMALL(Spielplan!$J$2:$J$19,8),Spielplan!$J$2:$J$19,0)+1,2,3),1)",
  "repair:indirect_address_cross_sheet:=INDIRECT(ADDRESS(SMALL(Spielplan!$J$2:$J$19,8)+1,2,3,,\"Spielplan\"),1)": "=INDIRECT(\"$Spielplan.\" & ADDRESS(SMALL(Spielplan!$J$2:$J$19,8)+1,2,3,))",
  "repair:indirect_address_cross_sheet:=INDIRECT(ADDRESS(MATCH(SMALL(Spielplan!$J$2:$J$19,9),Spielplan!$J$2:$J$19,0)+1,2,3,,\"Spielplan\"),1)": "=INDIRECT(\"$Spielplan.\" & ADDRESS(MATCH(SMALL(Spielplan!$J$2:$J$19,9),Spielplan!$J$2:$J$19,0)+1,2,3),1)",
  "repair:indirect_address_cross_sheet:=INDIRECT(ADDRESS(SMALL(Spielplan!$J$2:$J$19,9)+1,2,3,,\"Spielplan\"),1)": "=INDIRECT(\"$Spielplan.\" & ADDRESS(SMALL(Spielplan!$J$2:$J$19,9)+1,2,3,))",
  "repair:indirect_address_cross_sheet:=INDIRECT(ADDRESS(MATCH(SMALL(Spielplan!$K$2:$K$19,1),Spielplan!$K$2:$K$19,0)+1,2,3,,\"Spielplan\"),1)": "=INDIRECT(\"$Spielplan.\" & ADDRESS(MATCH(SMALL(Spielplan!$K$2:$K$19,1),Spielplan!$K$2:$K$19,0)+1,2,3),1)",
  "repair:indirect_address_cross_sheet:=INDIRECT(ADDRESS(SMALL(Spielplan!$K$2:$K$19,1)+1,2,3,,\"Spielplan\"),1)": "=INDIRECT(\"$Spielplan.\" & ADDRESS(SMALL(Spielplan!$K$2:$K$19,1)+1,2,3,),1)",
  "repair:indirect_address_cross_sheet:=INDIRECT(ADDRESS(MATCH(SMALL(Spielplan!$K$2:$K$19,2),Spielplan!$K$2:$K$19,0)+1,2,3,,\"Spielplan\"),1)": "=INDIRECT(\"$Spielplan.\" & ADDRESS(MATCH(SMALL(Spielplan!$K$2:$K$19,2),Spielplan!$K$2:$K$19,0)+1,2,3),1)",
  "repair:indirect_address_cross_sheet:=INDIRECT(ADDRESS(SMALL(Spielplan!$K$2:$K$19,2)+1,2,3,,\"Spielplan\"),1)": "=INDIRECT(\"$Spielplan.\" & ADDRESS(SMALL(Spielplan!$K$2:$K$19,2)+1,2,3,))",
  "repair:indirect_address_cross_sheet:=INDIRECT(ADDRESS(MATCH(SMALL(Spielplan!$K$2:$K$19,3),Spielplan!$K$2:$K$19,0)+1,2,3,,\"Spielplan\"),1)": "=INDIRECT(\"$Spielplan.\" & ADDRESS(MATCH(SMALL(Spielplan!$K$2:$K$19,3),Spielplan!$K$2:$K$19,0)+1,2,3),1)",
  "repair:indirect_address_cross_sheet:=INDIRECT(ADDRESS(SMALL(Spielplan!$K$2:$K$19,3)+1,2,3,,\"Spielplan\"),1)": "=INDIRECT(\"$Spielplan.\" & ADDRESS(SMALL(Spielplan!$K$2:$K$19,3)+1,2,3,))"
}